authix/__init__.py
authix/api.py
authix/asgi.py
authix/version.py
authix/core/config.py
authix/core/service_container.py
authix/data/__init__.py
authix/data/query_exceptions.py
authix/data/refresh_token/__init__.py
authix/data/refresh_token/refresh_token_queries.py
authix/data/refresh_token/queries/__init__.py
authix/data/refresh_token/queries/in_memory.py
authix/data/refresh_token/queries/redis.py
authix/data/users/__init__.py
authix/data/users/model.py
authix/data/users/user_queries.py
authix/data/users/queries/__init__.py
authix/data/users/queries/in_memory.py
authix/data/users/queries/mongodb.py
authix/domain/__init__.py
authix/domain/device_id.py
authix/domain/domain_exceptions.py
authix/domain/authentication/__init__.py
authix/domain/authentication/service.py
authix/domain/key/__init__.py
authix/domain/key/service.py
authix/domain/password_validation/__init__.py
authix/domain/password_validation/password_validator.py
authix/domain/password_validation/validator.py
authix/domain/password_validation/validators/__init__.py
authix/domain/password_validation/validators/ascii_only.py
authix/domain/password_validation/validators/max_length.py
authix/domain/password_validation/validators/min_digits.py
authix/domain/password_validation/validators/min_length.py
authix/domain/password_validation/validators/min_lowercase.py
authix/domain/password_validation/validators/min_special_symbols.py
authix/domain/password_validation/validators/min_uppercase.py
authix/domain/registration/__init__.py
authix/domain/registration/service.py
authix/domain/revocation/__init__.py
authix/domain/revocation/event.py
authix/domain/revocation/publisher.py
authix/domain/revocation/service.py
authix/domain/revocation/publishers/__init__.py
authix/domain/revocation/publishers/kafka_publisher.py
authix/domain/token/__init__.py
authix/domain/token/password_hashing_strategy.py
authix/domain/token/service.py
authix/domain/token/password_hashing_strategies/__init__.py
authix-0.0.7.dist-info/METADATA
authix-0.0.7.dist-info/WHEEL
authix-0.0.7.dist-info/top_level.txt
authix-0.0.7.dist-info/RECORD
